pandaspipe/__init__.py
pandaspipe/_util.py
pandaspipe/base.py
pandaspipe/converter.py
pandaspipe/data.py
pandaspipe/filter.py
pandaspipe/mapper.py
pandaspipe/merger.py
pandaspipe/pipeline.py
pandaspipe-0.2.1.dist-info/DESCRIPTION.rst
pandaspipe-0.2.1.dist-info/METADATA
pandaspipe-0.2.1.dist-info/RECORD
pandaspipe-0.2.1.dist-info/WHEEL
pandaspipe-0.2.1.dist-info/metadata.json
pandaspipe-0.2.1.dist-info/top_level.txt
