Metadata-Version: 2.0
Name: pandaspipe
Version: 0.2.1
Summary: Tool to process pandas dataframes with pipe
Home-page: http://siredvin.github.io/
Author: siredvin
Author-email: siredvin.dark@gmail.com
License: Apache 2.0
Platform: UNKNOWN
